LICENSE.txt
README.md
setup.py
perpy/__init__.py
perpy/clustering.py
perpy.egg-info/PKG-INFO
perpy.egg-info/SOURCES.txt
perpy.egg-info/dependency_links.txt
perpy.egg-info/requires.txt
perpy.egg-info/top_level.txt
perpy/ops/cpu/dist.cc
perpy/ops/cpu/dist.dll
perpy/ops/cpu/dist.so
perpy/ops/cpu/dist32.dll