Metadata-Version: 2.1
Name: perpy
Version: 0.2.7
Summary: Functions commonly used in computer paper writing and scientific research.
Home-page: https://github.com/Very-Handsome9/perpy.git
Author: Yongbiao Li
Author-email: yongbiaoli@yeah.net
License: MIT
Platform: UNKNOWN
Classifier: Programming Language :: Python :: 3
Classifier: License :: OSI Approved :: MIT License
Classifier: Operating System :: OS Independent
Requires-Python: >=3.0
